lorenz.py
simple_python_package-0.5.0.dist-info/METADATA
simple_python_package-0.5.0.dist-info/WHEEL
simple_python_package-0.5.0.dist-info/licenses/LICENSE
simple_python_package-0.5.0.dist-info/RECORD
