Metadata-Version: 2.4
Name: simple-python-package
Version: 0.5.0
Summary: A project template for publication of simple Python packages to PyPI
License: GPLv3
License-File: LICENSE
Keywords: Python,PyPI,DevOps,open-source
Author: gperdrizet
Author-email: george@perdrizet.org
Requires-Python: >=3.10
Classifier: Development Status :: 4 - Beta
Classifier: Intended Audience :: Developers
Classifier: Intended Audience :: Science/Research
Classifier: License :: Other/Proprietary License
Classifier: Programming Language :: Python :: 3
Classifier: Programming Language :: Python :: 3.10
Classifier: Programming Language :: Python :: 3.11
Classifier: Programming Language :: Python :: 3.12
Classifier: Programming Language :: Python :: 3.13
Classifier: Programming Language :: Python :: 3.14
Classifier: Topic :: Scientific/Engineering
Classifier: Topic :: Scientific/Engineering :: Mathematics
Classifier: Topic :: Software Development :: Libraries :: Python Modules
Requires-Dist: matplotlib
Requires-Dist: pandas
Project-URL: Documentation, https://gperdrizet.github.io/simple-python-package/README.MD
Project-URL: Homepage, https://github.com/gperdrizet/simple-python-package
Project-URL: Issues, https://github.com/gperdrizet/simple-python-package/issues
Project-URL: PyPI, https://pypi.org/project/simple-python-package
Project-URL: Repository, https://github.com/gperdrizet/simple-python-package
